scikitlearnn/__init__.py
scikitlearnn/all_R_codes.py
scikitlearnn/bloom_FM.py
scikitlearnn/decisiontree.py
scikitlearnn/ensemble.py
scikitlearnn/gradient.py
scikitlearnn/linearreg.py
scikitlearnn/logisticreg.py
scikitlearnn/pca.py
scikitlearnn/preprocessing.py
scikitlearnn/svm.py
scikitlearnn/tinyurl_codes.py
scikitlearnn-0.5.dist-info/METADATA
scikitlearnn-0.5.dist-info/WHEEL
scikitlearnn-0.5.dist-info/top_level.txt
scikitlearnn-0.5.dist-info/RECORD
