Metadata-Version: 2.1
Name: scikitlearnn
Version: 0.5
Summary: A package for doing cool stuff
Home-page: UNKNOWN
Author: Your Name
Author-email: your@email.com
License: UNKNOWN
Platform: UNKNOWN
